{
  "content": [
    {
      "content": null,
      "created": "2023-03-06T10:49:54.182905Z",
      "format": null,
      "last_modified": "2023-03-06T10:48:11.882534Z",
      "mimetype": null,
      "name": "introduction.ipynb",
      "path": "introduction.ipynb",
      "size": 13817,
      "type": "notebook",
      "writable": true
    }
  ],
  "created": "2023-03-06T10:49:54.182905Z",
  "format": "json",
  "last_modified": "2023-03-06T10:49:54.182905Z",
  "mimetype": null,
  "name": "",
  "path": "",
  "size": null,
  "type": "directory",
  "writable": true
}